MANIFEST.in
README.md
setup.py
faker_e164/__init__.py
faker_e164/providers.py
faker_e164.egg-info/PKG-INFO
faker_e164.egg-info/SOURCES.txt
faker_e164.egg-info/dependency_links.txt
faker_e164.egg-info/requires.txt
faker_e164.egg-info/top_level.txt
faker_e164/__pycache__/__init__.cpython-35.pyc
faker_e164/__pycache__/__init__.cpython-36.pyc
faker_e164/__pycache__/providers.cpython-35.pyc
faker_e164/__pycache__/providers.cpython-36.pyc