Metadata-Version: 1.1
Name: faker-e164
Version: 0.1.0
Summary: Faker Provider to generate phone numbers in E164 format.
Home-page: https://github.com/crowdcomms/faker-e164
Author: Adam Jacquier-Parr
Author-email: ajparr@crowdcomms.com.au
License: Apache
Platform: UNKNOWN
Classifier: Development Status :: 3 - Alpha
Classifier: Environment :: Console
Classifier: Intended Audience :: Developers
Classifier: License :: OSI Approved :: Apache Software License
Classifier: Operating System :: OS Independent
Classifier: Natural Language :: English
Classifier: Programming Language :: Python :: 3.3
Classifier: Programming Language :: Python :: 3.4
Classifier: Programming Language :: Python :: 3.5
Classifier: Programming Language :: Python :: 3.6
Classifier: Topic :: Software Development :: Libraries :: Python Modules
Classifier: Topic :: Software Development :: Testing
Classifier: Topic :: Utilities
